pyvethirtyeight/__init__.py
pyvethirtyeight-1.1.0.dist-info/WHEEL
pyvethirtyeight-1.1.0.dist-info/METADATA
pyvethirtyeight-1.1.0.dist-info/RECORD
