Metadata-Version: 1.2
Name: pyvethirtyeight
Version: 1.1.0
Summary: A Python wrapper for the 2016 FiveThirtyEight Presidential Election Forecast
Home-page: http://bcon.gdn
License: UNKNOWN
Author: Benjamin Congdon
Author-email: me@bcon.gdn
Classifier: License :: OSI Approved :: MIT License
Requires-Dist: beautifulsoup4 (==4.5.1)
Requires-Dist: bs4 (==0.0.1)
Requires-Dist: dateparser (==0.5.0)
Requires-Dist: nose (==1.3.7)
Requires-Dist: python-dateutil (==2.5.3)
Requires-Dist: pytz (==2016.7)
Requires-Dist: regex (==2016.9.22)
Requires-Dist: requests (==2.11.1)
Requires-Dist: six (==1.10.0)
Requires-Dist: tzlocal (==1.2.2)
